panpath/__init__.py
panpath/azure_async_client.py
panpath/azure_client.py
panpath/azure_path.py
panpath/base.py
panpath/clients.py
panpath/cloud.py
panpath/exceptions.py
panpath/gs_async_client.py
panpath/gs_client.py
panpath/gs_path.py
panpath/local_path.py
panpath/py.typed
panpath/registry.py
panpath/s3_async_client.py
panpath/s3_client.py
panpath/s3_path.py
panpath-0.4.9.dist-info/METADATA
panpath-0.4.9.dist-info/WHEEL
panpath-0.4.9.dist-info/licenses/LICENSE
panpath-0.4.9.dist-info/RECORD
