Metadata-Version: 2.4
Name: panpath
Version: 0.4.9
Summary: Universal sync/async local/cloud path library with pathlib-compatible interface
License: MIT
License-File: LICENSE
Keywords: path,pathlib,s3,gcs,azure,cloud,async,asyncio
Author: panpath contributors
Requires-Python: >=3.9,<4.0
Classifier: Development Status :: 3 - Alpha
Classifier: Intended Audience :: Developers
Classifier: License :: OSI Approved :: MIT License
Classifier: Programming Language :: Python :: 3
Classifier: Programming Language :: Python :: 3.9
Classifier: Programming Language :: Python :: 3.10
Classifier: Programming Language :: Python :: 3.11
Classifier: Programming Language :: Python :: 3.12
Classifier: Programming Language :: Python :: 3.13
Classifier: Programming Language :: Python :: 3.14
Classifier: Topic :: Software Development :: Libraries :: Python Modules
Classifier: Topic :: System :: Filesystems
Provides-Extra: all
Provides-Extra: all-async
Provides-Extra: all-sync
Provides-Extra: async-azure
Provides-Extra: async-gs
Provides-Extra: async-s3
Provides-Extra: azure
Provides-Extra: gs
Provides-Extra: s3
Requires-Dist: aioboto3 (>=11.0.0) ; extra == "async-s3" or extra == "all-async" or extra == "all"
Requires-Dist: aiofiles (>=23.0.0) ; extra == "async-s3" or extra == "async-gs" or extra == "async-azure" or extra == "all-async" or extra == "all"
Requires-Dist: azure-storage-blob (>=12.0.0) ; extra == "azure" or extra == "async-azure" or extra == "all-sync" or extra == "all-async" or extra == "all"
Requires-Dist: boto3 (>=1.20.0) ; extra == "s3" or extra == "all-sync" or extra == "all"
Requires-Dist: gcloud-aio-storage (>=9.5) ; extra == "async-gs" or extra == "all-async" or extra == "all"
Requires-Dist: google-cloud-storage (>=2.0.0) ; extra == "gs" or extra == "all-sync" or extra == "all"
Requires-Dist: typing-extensions (>=4.0.0)
Project-URL: Documentation, https://github.com/pwwang/panpath#readme
Project-URL: Homepage, https://github.com/pwwang/panpath
Project-URL: Repository, https://github.com/pwwang/panpath
